LICENSE
README.md
setup.cfg
setup.py
motu_profiler.egg-info/PKG-INFO
motu_profiler.egg-info/SOURCES.txt
motu_profiler.egg-info/dependency_links.txt
motu_profiler.egg-info/entry_points.txt
motu_profiler.egg-info/top_level.txt
motus/PEfiltering.py
motus/UTIL_log.py
motus/UTIL_log_col.py
motus/append.py
motus/convert_long_reads.py
motus/downloadDB.py
motus/map_genes_to_mOTUs.py
motus/map_mOTUs_to_LGs.py
motus/metaSNV_DistDiv.py
motus/metaSNV_Filtering_2.0.py
motus/motu_utilities.py
motus/motus.py
motus/msamtools_python.py
motus/print_CAMI.py
motus/runBWA.py
motus/runBWA_for_snv.py
motus/test.py