Metadata-Version: 2.1
Name: motu-profiler
Version: 3.1.0
Summary: Taxonomic profiling of metagenomes from diverse environments with mOTUs3
Home-page: https://github.com/motu-tool/mOTUs
Download-URL: https://github.com/motu-tool/mOTUs/archive/refs/tags/3.1.0.tar.gz
Author: Alessio Milanese
Author-email: alessiom@ethz.ch
License: GPLv3
Keywords: bioinformatics metagenomics taxonomic profiling
Classifier: Programming Language :: Python
Classifier: Programming Language :: Python :: 3
Classifier: Development Status :: 5 - Production/Stable
Classifier: Intended Audience :: Science/Research
Classifier: Topic :: Scientific/Engineering :: Bio-Informatics
Classifier: License :: OSI Approved :: GNU General Public License v3 (GPLv3)
Classifier: Operating System :: OS Independent
License-File: LICENSE
